{
    "name": "Kuftal Tunnel: Map 4",
    "filename": "kuftal_tunnel_4.png",
    "upperBoundX": "",
    "upperBoundY": "",
    "connections": {
        "136": {
            "hover": [
                [
                    [
                        [
                            119.99609,
                            173.5
                        ],
                        [
                            120.49609,
                            183.375
                        ],
                        [
                            113.24609,
                            183
                        ],
                        [
                            113.62109,
                            174.125
                        ]
                    ]
                ],
                [
                    [
                        [
                            147.62305,
                            90.6875
                        ],
                        [
                            141.18555,
                            91.1875
                        ],
                        [
                            141.68555,
                            100.5
                        ],
                        [
                            147.99805,
                            100.3125
                        ]
                    ]
                ]
            ],
            "pulse": [
                [
                    144.62305,
                    95.6875
                ],
                [
                    116.49805,
                    178.3125
                ]
            ]
        }
    }
}