{
    "name": "Yughott Grotto: Map 1",
    "filename": "yughott_grotto_1.png",
    "upperBoundX": "",
    "upperBoundY": "",
    "connections": {
        "115": {
            "hover": [
                [
                    134.99219,
                    39.5
                ],
                [
                    134.74219,
                    80.75
                ],
                [
                    108.24219,
                    81
                ],
                [
                    107.99219,
                    70
                ],
                [
                    113.99219,
                    65.75
                ],
                [
                    114.49219,
                    41.25
                ]
            ],
            "pulse": [
                [
                    111.24902,
                    75.6875
                ]
            ]
        },
        "110": {
            "hover": [
                [
                    146.24609,
                    110.375
                ],
                [
                    156.24609,
                    119.25
                ],
                [
                    173.49609,
                    119.125
                ],
                [
                    173.37109,
                    176.125
                ],
                [
                    164.24609,
                    175.625
                ],
                [
                    162.87109,
                    142.875
                ],
                [
                    158.99609,
                    148
                ],
                [
                    154.24609,
                    147.125
                ],
                [
                    152.12109,
                    123.25
                ],
                [
                    144.99609,
                    121.875
                ],
                [
                    134.24609,
                    131.375
                ],
                [
                    132.12109,
                    130.375
                ],
                [
                    131.62109,
                    118.75
                ]
            ],
            "pulse": [
                [
                    135.24902,
                    124.96875
                ],
                [
                    168.53027,
                    169.5
                ]
            ]
        }
    }
}