{
    "name": "Nashmau",
    "filename": "nashmau.png",
    "upperBoundX": "",
    "upperBoundY": "",
    "connections": {
        "329": {
            "hover": [
                [
                    [
                        [
                            147.77344,
                            106.98438
                        ],
                        [
                            152.35938,
                            88.53125
                        ],
                        [
                            152.46094,
                            51.79688
                        ],
                        [
                            133.64844,
                            52.14063
                        ],
                        [
                            133.71094,
                            88.76563
                        ],
                        [
                            143.46484,
                            106.96094
                        ]
                    ]
                ],
                [
                    [
                        [
                            164.30859,
                            123.83594
                        ],
                        [
                            180.55469,
                            117.51563
                        ],
                        [
                            181.60938,
                            109.90625
                        ],
                        [
                            202.96094,
                            109.29688
                        ],
                        [
                            203.86719,
                            149.01563
                        ],
                        [
                            180.99219,
                            148.45313
                        ],
                        [
                            181.39844,
                            132.04688
                        ],
                        [
                            164.32422,
                            128.83594
                        ]
                    ]
                ],
                [
                    [
                        [
                            128.83984,
                            132.19531
                        ],
                        [
                            132.80469,
                            150.29688
                        ],
                        [
                            139.39844,
                            149.89063
                        ],
                        [
                            139.67969,
                            184.29688
                        ],
                        [
                            117.42969,
                            184.39063
                        ],
                        [
                            118.42969,
                            150.85938
                        ],
                        [
                            124.32422,
                            132.30469
                        ]
                    ]
                ]
            ],
            "pulse": [
                [
                    126.52734,
                    132.14844
                ],
                [
                    164.19922,
                    126.38281
                ],
                [
                    145.63672,
                    107.03906
                ]
            ]
        },
        "295": {
            "hover": [
                [
                    101.61719,
                    110.48438
                ],
                [
                    101.86719,
                    123.82813
                ],
                [
                    84.58594,
                    124.17188
                ],
                [
                    84.96094,
                    110.32813
                ]
            ],
            "pulse": [
                [
                    96.43359,
                    115.91406
                ]
            ]
        }
    }
}