{
    "name": "The Shrine of Ru'Avitau: Map 1",
    "filename": "ruavitau-shrine_1.jpg",
    "upperBoundX": "",
    "upperBoundY": "",
    "connections": {
        "267": {
            "hover": [
                [
                    120.12109,
                    125.875
                ],
                [
                    106.24609,
                    125.875
                ],
                [
                    106.74609,
                    138.625
                ],
                [
                    119.99609,
                    137.5
                ]
            ],
            "pulse": [
                [
                    118.87109,
                    128.125
                ]
            ]
        },
        "271": {
            "hover": [
                [
                    [
                        [
                            148.74219,
                            129.5
                        ],
                        [
                            135.49219,
                            129.75
                        ],
                        [
                            135.49219,
                            143
                        ],
                        [
                            149.74219,
                            141.75
                        ]
                    ]
                ],
                [
                    [
                        [
                            100.49219,
                            114.25
                        ],
                        [
                            88.24219,
                            114
                        ],
                        [
                            87.49219,
                            129
                        ],
                        [
                            102.24219,
                            129
                        ]
                    ]
                ]
            ],
            "pulse": [
                [
                    143.74609,
                    136.25
                ],
                [
                    94.87109,
                    120.625
                ]
            ]
        }
    }
}