{
    "name": "Arrapago Reef: Map 5",
    "filename": "arrapago_reef_5.png",
    "upperBoundX": "",
    "upperBoundY": "",
    "connections": {
        "331": {
            "hover": [
                [
                    [
                        [
                            112.37956,
                            124.97043
                        ],
                        [
                            101.36908,
                            124.91787
                        ],
                        [
                            101.23769,
                            139.55473
                        ],
                        [
                            112.43212,
                            139.47589
                        ]
                    ]
                ],
                [
                    [
                        [
                            147.67383,
                            130.67822
                        ],
                        [
                            124.04104,
                            130.58429
                        ],
                        [
                            124.0782,
                            116.96415
                        ],
                        [
                            147.56504,
                            116.87125
                        ]
                    ]
                ]
            ],
            "pulse": [
                [
                    139.33691,
                    127.29224
                ],
                [
                    127.29004,
                    123.62036
                ],
                [
                    109.68066,
                    131.82349
                ]
            ]
        }
    }
}