{
    "name": "Konschtat Highlands",
    "filename": "konschtat_highlands.png",
    "bounds": [
        [
            -1277.26,
            -1248.05
        ],
        [
            1282.74,
            1311.95
        ]
    ],
    "connections": {
        "63": {
            "hover": [
                [
                    1149.411,
                    -411.01
                ],
                [
                    1055.661,
                    -404.76
                ],
                [
                    909.411,
                    -183.51
                ],
                [
                    904.411,
                    -132.26
                ],
                [
                    1068.161,
                    107.74
                ],
                [
                    1161.911,
                    102.74
                ]
            ],
            "pulse": [
                [
                    899.445,
                    -161.01
                ]
            ]
        },
        "119": {
            "hover": [
                [
                    209.411,
                    642.74
                ],
                [
                    329.411,
                    762.74
                ],
                [
                    421.911,
                    771.49
                ],
                [
                    409.411,
                    1041.49
                ],
                [
                    228.161,
                    1025.24
                ],
                [
                    223.161,
                    765.24
                ],
                [
                    178.161,
                    673.99
                ]
            ],
            "pulse": [
                [
                    196.476,
                    698.678
                ]
            ]
        },
        "143": {
            "hover": [
                [
                    -685.003,
                    80.24
                ],
                [
                    -895.003,
                    90.24
                ],
                [
                    -900.003,
                    557.74
                ],
                [
                    -690.003,
                    420.24
                ],
                [
                    -672.503,
                    145.24
                ]
            ],
            "pulse": [
                [
                    -663.641,
                    128.99
                ]
            ]
        },
        "147": {
            "hover": [
                [
                    1001.911,
                    223.99
                ],
                [
                    883.161,
                    225.24
                ],
                [
                    785.661,
                    493.99
                ],
                [
                    786.911,
                    585.24
                ],
                [
                    908.161,
                    901.49
                ],
                [
                    1020.661,
                    900.24
                ],
                [
                    1011.911,
                    236.49
                ]
            ],
            "pulse": [
                [
                    765.056,
                    528.99
                ]
            ]
        }
    },
    "mobSpawns": [
        [
            [
                "Enemies"
            ],
            "Mist Lizard",
            -151.078,
            -44.856,
            -420.416,
            10,
            12
        ],
        [
            [
                "Enemies"
            ],
            "Mist Lizard",
            -128.529,
            -45.684,
            -422.671,
            10,
            12
        ],
        [
            [
                "Enemies"
            ],
            "Mist Lizard",
            -118.322,
            -57.97,
            -552.02,
            10,
            12
        ],
        [
            [
                "Enemies"
            ],
            "Mist Lizard",
            -37.356,
            -57.312,
            -555.165,
            10,
            12
        ],
        [
            [
                "Enemies"
            ],
            "Mist Lizard",
            -136.629,
            -48.501,
            -446.881,
            10,
            12
        ],
        [
            [
                "Enemies"
            ],
            "Mist Lizard",
            -136.946,
            -47.878,
            -436.023,
            10,
            12
        ],
        [
            [
                "Enemies"
            ],
            "Strolling Sapling",
            -136.14,
            -47.109,
            -429.799,
            7,
            11
        ],
        [
            [
                "Enemies"
            ],
            "Strolling Sapling",
            -141.556,
            -49.49,
            -484.126,
            7,
            11
        ],
        [
            [
                "Enemies"
            ],
            "Strolling Sapling",
            -271,
            64,
            802,
            7,
            11
        ],
        [
            [
                "Enemies"
            ],
            "Strolling Sapling",
            -107.398,
            -41.361,
            -410.242,
            7,
            11
        ],
        [
            [
                "Enemies"
            ],
            "Strolling Sapling",
            -128.878,
            -56.599,
            -540.855,
            7,
            11
        ],
        [
            [
                "Enemies"
            ],
            "Strolling Sapling",
            -125.524,
            -44.968,
            -420.723,
            7,
            11
        ],
        [
            [
                "Enemies"
            ],
            "Rock Eater",
            -85.13,
            -55.812,
            -649.846,
            7,
            11
        ],
        [
            [
                "Enemies"
            ],
            "Rock Eater",
            -141.348,
            -60.499,
            -686.762,
            7,
            11
        ],
        [
            [
                "Enemies"
            ],
            "Rock Eater",
            -156.754,
            -63.381,
            -708.21,
            7,
            11
        ],
        [
            [
                "Enemies"
            ],
            "Rock Eater",
            -139.552,
            -59.568,
            -693.188,
            7,
            11
        ],
        [
            [
                "Enemies"
            ],
            "Rock Eater",
            -145.564,
            -62.7,
            -707.349,
            7,
            11
        ],
        [
            [
                "Enemies"
            ],
            "Rock Eater",
            -118.425,
            -57.893,
            -670.267,
            7,
            11
        ],
        [
            [
                "Enemies"
            ],
            "Goblin Thug",
            -121.538,
            -62.743,
            -649.776,
            8,
            10
        ],
        [
            [
                "Enemies"
            ],
            "Goblin Ambusher",
            -154.998,
            -63.308,
            -711.235,
            12,
            16
        ],
        [
            [
                "Enemies"
            ],
            "Goblin Weaver",
            -148.807,
            -62.782,
            -679.582,
            8,
            10
        ],
        [
            [
                "Enemies"
            ],
            "Goblin Butcher",
            -101,
            -57,
            -660,
            12,
            16
        ],
        [
            [
                "Enemies"
            ],
            "Goblin Thug",
            -77.823,
            -56.275,
            -670.291,
            8,
            10
        ],
        [
            [
                "Enemies"
            ],
            "Goblin Weaver",
            -98.272,
            -57.775,
            -662.657,
            8,
            10
        ],
        [
            [
                "Enemies"
            ],
            "Goblin Butcher",
            -97.796,
            -57.493,
            -660.834,
            12,
            16
        ],
        [
            [
                "Enemies"
            ],
            "Mist Lizard",
            284.143,
            -25.878,
            -443.59,
            10,
            12
        ],
        [
            [
                "Enemies"
            ],
            "Mist Lizard",
            295.701,
            -24.757,
            -443.328,
            10,
            12
        ],
        [
            [
                "Enemies"
            ],
            "Mist Lizard",
            390.079,
            -12.31,
            -363.865,
            10,
            12
        ],
        [
            [
                "Enemies"
            ],
            "Mist Lizard",
            355.577,
            -16.953,
            -430.784,
            10,
            12
        ],
        [
            [
                "Enemies"
            ],
            "Mist Lizard",
            318.848,
            -20.918,
            -455.298,
            10,
            12
        ],
        [
            [
                "Enemies"
            ],
            "Strolling Sapling",
            399.077,
            -8.335,
            -347.126,
            7,
            11
        ],
        [
            [
                "Enemies"
            ],
            "Strolling Sapling",
            317.842,
            -20.406,
            -450.267,
            7,
            11
        ],
        [
            [
                "Enemies"
            ],
            "Strolling Sapling",
            310.948,
            -19.847,
            -440.027,
            7,
            11
        ],
        [
            [
                "Enemies"
            ],
            "Strolling Sapling",
            337.95,
            -18.622,
            -451.718,
            7,
            11
        ],
        [
            [
                "Enemies"
            ],
            "Ghillie Dhu",
            387.0,
            -8.873,
            -338.999,
            16,
            18
        ],
        [
            [
                "Enemies"
            ],
            "Rock Eater",
            431.979,
            -13.461,
            -378.283,
            7,
            11
        ],
        [
            [
                "Enemies"
            ],
            "Rock Eater",
            402.186,
            -23.473,
            -431.614,
            7,
            11
        ],
        [
            [
                "Enemies"
            ],
            "Rock Eater",
            498.291,
            -15.424,
            -411.506,
            7,
            11
        ],
        [
            [
                "Enemies"
            ],
            "Young Quadav",
            375.276,
            -17.545,
            -413.568,
            8,
            10
        ],
        [
            [
                "Enemies"
            ],
            "Onyx Quadav",
            438.241,
            -13.32,
            -381.263,
            10,
            16
        ],
        [
            [
                "Enemies"
            ],
            "Amethyst Quadav",
            462.362,
            -13.501,
            -359.289,
            8,
            10
        ],
        [
            [
                "Enemies"
            ],
            "Amber Quadav",
            514,
            -16,
            -407,
            8,
            10
        ],
        [
            [
                "Enemies"
            ],
            "Young Quadav",
            503,
            -15,
            -424,
            8,
            10
        ],
        [
            [
                "Enemies"
            ],
            "Amethyst Quadav",
            496.785,
            -16.114,
            -421.315,
            8,
            10
        ],
        [
            [
                "Enemies"
            ],
            "Amber Quadav",
            499.752,
            -15.779,
            -418.372,
            8,
            10
        ],
        [
            [
                "Enemies"
            ],
            "Mist Lizard",
            377.877,
            2.503,
            22.975,
            10,
            12
        ],
        [
            [
                "Enemies"
            ],
            "Mist Lizard",
            256.498,
            15.021,
            47.851,
            10,
            12
        ],
        [
            [
                "Enemies"
            ],
            "Mist Lizard",
            396.703,
            10.477,
            62.373,
            10,
            12
        ],
        [
            [
                "Enemies"
            ],
            "Mist Lizard",
            356.308,
            14.155,
            73.873,
            10,
            12
        ],
        [
            [
                "Enemies"
            ],
            "Mist Lizard",
            412.98,
            9.439,
            65.27,
            10,
            12
        ],
        [
            [
                "Enemies"
            ],
            "Mist Lizard",
            271.91,
            0.04,
            -41.566,
            10,
            12
        ],
        [
            [
                "Enemies"
            ],
            "Huge Wasp",
            323.175,
            21.954,
            83.038,
            7,
            11
        ],
        [
            [
                "Enemies"
            ],
            "Huge Wasp",
            351.935,
            8.713,
            46.532,
            7,
            11
        ],
        [
            [
                "Enemies"
            ],
            "Huge Wasp",
            226.604,
            17.372,
            54.632,
            7,
            11
        ],
        [
            [
                "Enemies"
            ],
            "Huge Wasp",
            236.707,
            15.692,
            31.187,
            7,
            11
        ],
        [
            [
                "Enemies"
            ],
            "Huge Wasp",
            330.447,
            0.636,
            6.374,
            7,
            11
        ],
        [
            [
                "Enemies"
            ],
            "Huge Wasp",
            424.544,
            3.38,
            49.856,
            7,
            11
        ],
        [
            [
                "Enemies"
            ],
            "Strolling Sapling",
            390.404,
            0.392,
            -1.681,
            7,
            11
        ],
        [
            [
                "Enemies"
            ],
            "Strolling Sapling",
            380.121,
            13.019,
            67.683,
            7,
            11
        ],
        [
            [
                "Enemies"
            ],
            "Mist Lizard",
            336.272,
            23.248,
            192.169,
            10,
            12
        ],
        [
            [
                "Enemies"
            ],
            "Mist Lizard",
            362.136,
            23.264,
            193.4,
            10,
            12
        ],
        [
            [
                "Enemies"
            ],
            "Mist Lizard",
            459.062,
            19.708,
            178.461,
            10,
            12
        ],
        [
            [
                "Enemies"
            ],
            "Huge Wasp",
            324.302,
            24.12,
            189.477,
            7,
            11
        ],
        [
            [
                "Enemies"
            ],
            "Huge Wasp",
            244.243,
            23.581,
            141.043,
            7,
            11
        ],
        [
            [
                "Enemies"
            ],
            "Huge Wasp",
            359.407,
            16.573,
            105.864,
            7,
            11
        ],
        [
            [
                "Enemies"
            ],
            "Huge Wasp",
            283.673,
            24.345,
            109.079,
            7,
            11
        ],
        [
            [
                "Enemies"
            ],
            "Strolling Sapling",
            272.901,
            23.728,
            146.096,
            7,
            11
        ],
        [
            [
                "Enemies"
            ],
            "Strolling Sapling",
            463.239,
            10.861,
            127.264,
            7,
            11
        ],
        [
            [
                "Enemies"
            ],
            "Strolling Sapling",
            317.589,
            23.516,
            110.541,
            7,
            11
        ],
        [
            [
                "Enemies"
            ],
            "Strolling Sapling",
            348.56,
            23.998,
            208.237,
            7,
            11
        ],
        [
            [
                "Enemies"
            ],
            "Strolling Sapling",
            382,
            24,
            259,
            7,
            11
        ],
        [
            [
                "Enemies"
            ],
            "Strolling Sapling",
            261.549,
            24.83,
            110.827,
            7,
            11
        ],
        [
            [
                "Enemies"
            ],
            "Huge Wasp",
            506.118,
            14.962,
            185.235,
            7,
            11
        ],
        [
            [
                "Enemies"
            ],
            "Huge Wasp",
            549.752,
            15.969,
            173.121,
            7,
            11
        ],
        [
            [
                "Enemies"
            ],
            "Strolling Sapling",
            535.929,
            11.202,
            161.218,
            7,
            11
        ],
        [
            [
                "Enemies"
            ],
            "Strolling Sapling",
            565.252,
            19.966,
            183.923,
            7,
            11
        ],
        [
            [
                "Enemies"
            ],
            "Rock Eater",
            593.34,
            23.285,
            165.846,
            7,
            11
        ],
        [
            [
                "Enemies"
            ],
            "Rock Eater",
            642.249,
            23.05,
            131.419,
            7,
            11
        ],
        [
            [
                "Enemies"
            ],
            "Rock Eater",
            619.719,
            21.037,
            134.751,
            7,
            11
        ],
        [
            [
                "Enemies"
            ],
            "Rock Eater",
            633.091,
            22.233,
            161.557,
            7,
            11
        ],
        [
            [
                "Enemies"
            ],
            "Rock Eater",
            676.117,
            22.21,
            197.821,
            7,
            11
        ],
        [
            [
                "Enemies"
            ],
            "Rock Eater",
            575.445,
            18.641,
            156.881,
            7,
            11
        ],
        [
            [
                "Enemies"
            ],
            "Ghost",
            623.298,
            22.06,
            135.687,
            15,
            17
        ],
        [
            [
                "Enemies"
            ],
            "Ghost",
            514.723,
            10.53,
            172.762,
            15,
            17
        ],
        [
            [
                "Enemies"
            ],
            "Ghost",
            673.379,
            23.427,
            176.089,
            15,
            17
        ],
        [
            [
                "Enemies"
            ],
            "Young Quadav",
            265.113,
            15.431,
            42.001,
            8,
            10
        ],
        [
            [
                "Enemies"
            ],
            "Young Quadav",
            422.499,
            23.466,
            190.715,
            8,
            10
        ],
        [
            [
                "Enemies"
            ],
            "Veteran Quadav",
            593,
            23,
            205,
            10,
            16
        ],
        [
            [
                "Enemies"
            ],
            "Greater Quadav",
            418.088,
            10.79,
            79.852,
            10,
            16
        ],
        [
            [
                "Enemies"
            ],
            "Onyx Quadav",
            610.562,
            20.472,
            139.956,
            10,
            16
        ],
        [
            [
                "Enemies"
            ],
            "Amethyst Quadav",
            628.755,
            22.11,
            129.301,
            8,
            10
        ],
        [
            [
                "Enemies"
            ],
            "Amber Quadav",
            402.109,
            9.193,
            52.888,
            8,
            10
        ],
        [
            [
                "Enemies"
            ],
            "Skeleton Warrior",
            526.456,
            8.858,
            167.034,
            10,
            12
        ],
        [
            [
                "Enemies"
            ],
            "Skeleton Warrior",
            345.299,
            19.741,
            166.122,
            10,
            12
        ],
        [
            [
                "Enemies"
            ],
            "Skeleton Sorcerer",
            412.034,
            16.215,
            130.671,
            11,
            13
        ],
        [
            [
                "Enemies"
            ],
            "Thunder Elemental",
            261.908,
            15.172,
            45.673,
            18,
            20
        ],
        [
            [
                "Enemies"
            ],
            "Mist Lizard",
            287.124,
            23.877,
            310.817,
            10,
            12
        ],
        [
            [
                "Enemies"
            ],
            "Mist Lizard",
            451.325,
            32.107,
            308.275,
            10,
            12
        ],
        [
            [
                "Enemies"
            ],
            "Mist Lizard",
            400.329,
            26.317,
            296.178,
            10,
            12
        ],
        [
            [
                "Enemies"
            ],
            "Huge Wasp",
            335.788,
            28.02,
            378.874,
            7,
            11
        ],
        [
            [
                "Enemies"
            ],
            "Huge Wasp",
            420.849,
            33.556,
            356.294,
            7,
            11
        ],
        [
            [
                "Enemies"
            ],
            "Huge Wasp",
            349.606,
            24.127,
            234.694,
            7,
            11
        ],
        [
            [
                "Enemies"
            ],
            "Huge Wasp",
            442.869,
            24.722,
            247.804,
            7,
            11
        ],
        [
            [
                "Enemies"
            ],
            "Strolling Sapling",
            408.942,
            32.251,
            340.512,
            7,
            11
        ],
        [
            [
                "Enemies"
            ],
            "Strolling Sapling",
            240.04,
            23.555,
            304.287,
            7,
            11
        ],
        [
            [
                "Enemies"
            ],
            "Strolling Sapling",
            458.664,
            34.098,
            319.992,
            7,
            11
        ],
        [
            [
                "Enemies"
            ],
            "Strolling Sapling",
            355.742,
            31.208,
            357.561,
            7,
            11
        ],
        [
            [
                "Enemies"
            ],
            "Strolling Sapling",
            452.427,
            26.806,
            260.52,
            7,
            11
        ],
        [
            [
                "Enemies"
            ],
            "Strolling Sapling",
            336.417,
            24.705,
            246.563,
            7,
            11
        ],
        [
            [
                "Enemies"
            ],
            "Poltergeist",
            555.848,
            36.815,
            408.295,
            18,
            20
        ],
        [
            [
                "Enemies"
            ],
            "Poltergeist",
            573,
            40,
            465,
            18,
            20
        ],
        [
            [
                "Enemies"
            ],
            "Poltergeist",
            583.771,
            22.467,
            462.726,
            18,
            20
        ],
        [
            [
                "Enemies"
            ],
            "Poltergeist",
            459.714,
            25.343,
            240.892,
            18,
            20
        ],
        [
            [
                "Enemies"
            ],
            "Poltergeist",
            483,
            28,
            261,
            18,
            20
        ],
        [
            [
                "Enemies"
            ],
            "Mist Lizard",
            190.147,
            24.048,
            390.542,
            10,
            12
        ],
        [
            [
                "Enemies"
            ],
            "Mist Lizard",
            186.661,
            23.108,
            410.509,
            10,
            12
        ],
        [
            [
                "Enemies"
            ],
            "Mist Lizard",
            232.005,
            23.172,
            478.276,
            10,
            12
        ],
        [
            [
                "Enemies"
            ],
            "Mist Lizard",
            392.252,
            32.01,
            524.866,
            10,
            12
        ],
        [
            [
                "Enemies"
            ],
            "Mist Lizard",
            318.304,
            23.949,
            399.301,
            10,
            12
        ],
        [
            [
                "Enemies"
            ],
            "Mist Lizard",
            392.067,
            32.111,
            506.365,
            10,
            12
        ],
        [
            [
                "Enemies"
            ],
            "Huge Wasp",
            337.655,
            30.838,
            592.66,
            7,
            11
        ],
        [
            [
                "Enemies"
            ],
            "Huge Wasp",
            336.797,
            24.456,
            415.198,
            7,
            11
        ],
        [
            [
                "Enemies"
            ],
            "Huge Wasp",
            207.898,
            31.171,
            540.164,
            7,
            11
        ],
        [
            [
                "Enemies"
            ],
            "Strolling Sapling",
            387.572,
            31.485,
            470.046,
            7,
            11
        ],
        [
            [
                "Enemies"
            ],
            "Strolling Sapling",
            286.738,
            23.044,
            391.069,
            7,
            11
        ],
        [
            [
                "Enemies"
            ],
            "Strolling Sapling",
            343.98,
            30.059,
            496.523,
            7,
            11
        ],
        [
            [
                "Enemies"
            ],
            "Mist Lizard",
            485.09,
            38.439,
            549.859,
            10,
            12
        ],
        [
            [
                "Enemies"
            ],
            "Mist Lizard",
            485.686,
            30.929,
            628.414,
            10,
            12
        ],
        [
            [
                "Enemies"
            ],
            "Mist Lizard",
            419.216,
            31.774,
            393.886,
            10,
            12
        ],
        [
            [
                "Enemies"
            ],
            "Mist Lizard",
            533.717,
            38.451,
            467.773,
            10,
            12
        ],
        [
            [
                "Enemies"
            ],
            "Huge Wasp",
            442.329,
            31.772,
            474.729,
            7,
            11
        ],
        [
            [
                "Enemies"
            ],
            "Huge Wasp",
            428.978,
            32.009,
            405.513,
            7,
            11
        ],
        [
            [
                "Enemies"
            ],
            "Huge Wasp",
            523.876,
            32.314,
            440.735,
            7,
            11
        ],
        [
            [
                "Enemies"
            ],
            "Huge Wasp",
            538.706,
            38.568,
            469.883,
            7,
            11
        ],
        [
            [
                "Enemies"
            ],
            "Strolling Sapling",
            438.292,
            30.881,
            447.383,
            7,
            11
        ],
        [
            [
                "Enemies"
            ],
            "Strolling Sapling",
            476.989,
            31.878,
            355.308,
            7,
            11
        ],
        [
            [
                "Enemies"
            ],
            "Strolling Sapling",
            389.672,
            32.343,
            401.477,
            7,
            11
        ],
        [
            [
                "Enemies"
            ],
            "Strolling Sapling",
            416.931,
            31.624,
            444.195,
            7,
            11
        ],
        [
            [
                "Enemies"
            ],
            "Veteran Quadav",
            435.249,
            31.537,
            322.498,
            10,
            16
        ],
        [
            [
                "Enemies"
            ],
            "Greater Quadav",
            357.755,
            30.16,
            563.38,
            10,
            16
        ],
        [
            [
                "Enemies"
            ],
            "Onyx Quadav",
            439.154,
            24.478,
            245.863,
            10,
            16
        ],
        [
            [
                "Enemies"
            ],
            "Amethyst Quadav",
            531.658,
            34.3,
            438.085,
            8,
            10
        ],
        [
            [
                "Enemies"
            ],
            "Amber Quadav",
            446,
            32,
            563,
            8,
            10
        ],
        [
            [
                "Enemies"
            ],
            "Skeleton Warrior",
            449.625,
            32.242,
            287.894,
            10,
            12
        ],
        [
            [
                "Enemies"
            ],
            "Skeleton Warrior",
            442.851,
            31.835,
            325.697,
            10,
            12
        ],
        [
            [
                "Enemies"
            ],
            "Skeleton Sorcerer",
            385.827,
            32.136,
            505.072,
            11,
            13
        ],
        [
            [
                "Enemies"
            ],
            "Grenade",
            391.101,
            32.505,
            538.061,
            15,
            17
        ],
        [
            [
                "Enemies"
            ],
            "Veteran Quadav",
            379.4,
            32.014,
            537.655,
            10,
            16
        ],
        [
            [
                "Enemies"
            ],
            "Amethyst Quadav",
            380.042,
            32.098,
            543.204,
            8,
            10
        ],
        [
            [
                "Enemies"
            ],
            "Amber Quadav",
            385,
            31,
            541,
            8,
            10
        ],
        [
            [
                "Enemies"
            ],
            "Rock Eater",
            634.746,
            38.172,
            431.791,
            7,
            11
        ],
        [
            [
                "Enemies"
            ],
            "Rock Eater",
            600.325,
            38.463,
            431.43,
            7,
            11
        ],
        [
            [
                "Enemies"
            ],
            "Rock Eater",
            561.872,
            38.436,
            398.344,
            7,
            11
        ],
        [
            [
                "Enemies"
            ],
            "Rock Eater",
            590.08,
            32.746,
            399.377,
            7,
            11
        ],
        [
            [
                "Enemies"
            ],
            "Mist Lizard",
            -128.765,
            -20.678,
            -174.672,
            10,
            12
        ],
        [
            [
                "Enemies"
            ],
            "Mist Lizard",
            -213.016,
            -23.638,
            -238.328,
            10,
            12
        ],
        [
            [
                "Enemies"
            ],
            "Mist Lizard",
            -200.179,
            -24.009,
            -220.467,
            10,
            12
        ],
        [
            [
                "Enemies"
            ],
            "Mist Lizard",
            -217.934,
            -22.283,
            -204.046,
            10,
            12
        ],
        [
            [
                "Enemies"
            ],
            "Mist Lizard",
            -125.299,
            -21,
            -173.03,
            10,
            12
        ],
        [
            [
                "Enemies"
            ],
            "Huge Wasp",
            -195.499,
            -33.296,
            -260.058,
            7,
            11
        ],
        [
            [
                "Enemies"
            ],
            "Huge Wasp",
            -153.597,
            -24.152,
            -187.899,
            7,
            11
        ],
        [
            [
                "Enemies"
            ],
            "Huge Wasp",
            -314.898,
            -39.294,
            -285.747,
            7,
            11
        ],
        [
            [
                "Enemies"
            ],
            "Huge Wasp",
            -163.56,
            -10.082,
            -77.174,
            7,
            11
        ],
        [
            [
                "Enemies"
            ],
            "Huge Wasp",
            -88.475,
            -25.663,
            -186.376,
            7,
            11
        ],
        [
            [
                "Enemies"
            ],
            "Mad Sheep",
            -165.785,
            -33.939,
            -245.381,
            11,
            14
        ],
        [
            [
                "Enemies"
            ],
            "Mad Sheep",
            -217.379,
            -24.069,
            -218.222,
            11,
            14
        ],
        [
            [
                "Enemies"
            ],
            "Strolling Sapling",
            -294.884,
            -30.16,
            -227.337,
            7,
            11
        ],
        [
            [
                "Enemies"
            ],
            "Strolling Sapling",
            -232.511,
            -24.538,
            -241.239,
            7,
            11
        ],
        [
            [
                "Enemies"
            ],
            "Wolf Zombie",
            -167.521,
            -13.832,
            -105.744,
            8,
            10
        ],
        [
            [
                "Enemies"
            ],
            "Mist Lizard",
            -417.989,
            -21.214,
            -215.004,
            10,
            12
        ],
        [
            [
                "Enemies"
            ],
            "Mist Lizard",
            -359.283,
            -27.213,
            -271.39,
            10,
            12
        ],
        [
            [
                "Enemies"
            ],
            "Huge Wasp",
            -369.62,
            -7.965,
            -149.38,
            7,
            11
        ],
        [
            [
                "Enemies"
            ],
            "Huge Wasp",
            -403.001,
            -0.46,
            -159.636,
            7,
            11
        ],
        [
            [
                "Enemies"
            ],
            "Mad Sheep",
            -446.567,
            -16.371,
            -198.068,
            11,
            14
        ],
        [
            [
                "Enemies"
            ],
            "Mad Sheep",
            -472.242,
            -26.109,
            -234.299,
            11,
            14
        ],
        [
            [
                "Enemies"
            ],
            "Mad Sheep",
            -415.904,
            -26.456,
            -230.069,
            11,
            14
        ],
        [
            [
                "Enemies"
            ],
            "Mad Sheep",
            -397.968,
            -13.67,
            -183.734,
            11,
            14
        ],
        [
            [
                "Enemies"
            ],
            "Mad Sheep",
            -436.817,
            -19.236,
            -210.597,
            11,
            14
        ],
        [
            [
                "Enemies"
            ],
            "Strolling Sapling",
            -353.452,
            -19.243,
            -202.403,
            7,
            11
        ],
        [
            [
                "Enemies"
            ],
            "Strolling Sapling",
            -446.937,
            -14.418,
            -189.802,
            7,
            11
        ],
        [
            [
                "Enemies"
            ],
            "Wolf Zombie",
            -319.756,
            -18.233,
            -168.804,
            8,
            10
        ],
        [
            [
                "Enemies"
            ],
            "Goblin Thug",
            -182.379,
            -13.165,
            -131.896,
            8,
            10
        ],
        [
            [
                "Enemies"
            ],
            "Goblin Thug",
            -250.719,
            -25.973,
            -212.339,
            8,
            10
        ],
        [
            [
                "Enemies"
            ],
            "Goblin Ambusher",
            -208.004,
            -14.059,
            -140.714,
            12,
            16
        ],
        [
            [
                "Enemies"
            ],
            "Goblin Weaver",
            -249.414,
            -27.726,
            -240.165,
            8,
            10
        ],
        [
            [
                "Enemies"
            ],
            "Goblin Tinkerer",
            -274.849,
            -37.622,
            -258.608,
            12,
            16
        ],
        [
            [
                "Enemies"
            ],
            "Goblin Butcher",
            -423.118,
            -14.719,
            -192.018,
            12,
            16
        ],
        [
            [
                "Enemies"
            ],
            "Skeleton Warrior",
            -403.593,
            -0.936,
            -164.908,
            10,
            12
        ],
        [
            [
                "Enemies"
            ],
            "Skeleton Sorcerer",
            -177.81,
            -48.472,
            -447.798,
            11,
            13
        ],
        [
            [
                "Enemies"
            ],
            "Earth Elemental",
            -227.102,
            -19.883,
            -177.863,
            18,
            20
        ],
        [
            [
                "Enemies"
            ],
            "Mist Lizard",
            -509.539,
            3.559,
            -20.947,
            10,
            12
        ],
        [
            [
                "Enemies"
            ],
            "Mist Lizard",
            -540.274,
            0.174,
            32.872,
            10,
            12
        ],
        [
            [
                "Enemies"
            ],
            "Huge Wasp",
            -495.243,
            -1.238,
            -96.943,
            7,
            11
        ],
        [
            [
                "Enemies"
            ],
            "Huge Wasp",
            -478.452,
            0.207,
            -65.931,
            7,
            11
        ],
        [
            [
                "Enemies"
            ],
            "Huge Wasp",
            -467.165,
            9.483,
            -20.798,
            7,
            11
        ],
        [
            [
                "Enemies"
            ],
            "Huge Wasp",
            -490.504,
            -2.313,
            -66.083,
            7,
            11
        ],
        [
            [
                "Enemies"
            ],
            "Huge Wasp",
            -516.484,
            -8.992,
            -133.965,
            7,
            11
        ],
        [
            [
                "Enemies"
            ],
            "Mad Sheep",
            -503.612,
            -1.722,
            -102.185,
            11,
            14
        ],
        [
            [
                "Enemies"
            ],
            "Mad Sheep",
            -470.446,
            11.605,
            -4.98,
            11,
            14
        ],
        [
            [
                "Enemies"
            ],
            "Strolling Sapling",
            -463.714,
            10.293,
            116.188,
            7,
            11
        ],
        [
            [
                "Enemies"
            ],
            "Strolling Sapling",
            -476.309,
            -0.848,
            -69.801,
            7,
            11
        ],
        [
            [
                "Enemies"
            ],
            "Highlander Lizard",
            -499.0,
            2.901,
            -48.0,
            27,
            28
        ],
        [
            [
                "Enemies"
            ],
            "Huge Wasp",
            -188.999,
            -3.852,
            -75.076,
            7,
            11
        ],
        [
            [
                "Enemies"
            ],
            "Huge Wasp",
            -289.566,
            -16.031,
            -130.469,
            7,
            11
        ],
        [
            [
                "Enemies"
            ],
            "Mad Sheep",
            -239.915,
            0.42,
            -63.1,
            11,
            14
        ],
        [
            [
                "Enemies"
            ],
            "Mad Sheep",
            -305.204,
            -11.695,
            -96.078,
            11,
            14
        ],
        [
            [
                "Enemies"
            ],
            "Mad Sheep",
            -329.002,
            -13.798,
            -138.143,
            11,
            14
        ],
        [
            [
                "Enemies"
            ],
            "Mad Sheep",
            -324.817,
            -15.194,
            -107.909,
            11,
            14
        ],
        [
            [
                "Enemies"
            ],
            "Mad Sheep",
            -247.377,
            -10.703,
            -101.932,
            11,
            14
        ],
        [
            [
                "Enemies"
            ],
            "Stray Mary",
            -257.465,
            -15.805,
            -117.638,
            19,
            20
        ],
        [
            [
                "Enemies"
            ],
            "Strolling Sapling",
            -319.557,
            -9.45,
            -88.829,
            7,
            11
        ],
        [
            [
                "Enemies"
            ],
            "Strolling Sapling",
            -367.359,
            -1.358,
            -80.909,
            7,
            11
        ],
        [
            [
                "Enemies"
            ],
            "Wolf Zombie",
            -248.949,
            -15.684,
            -116.538,
            8,
            10
        ],
        [
            [
                "Enemies"
            ],
            "Huge Wasp",
            -449.655,
            7.795,
            -35.259,
            7,
            11
        ],
        [
            [
                "Enemies"
            ],
            "Huge Wasp",
            -442.376,
            0.444,
            -76.893,
            7,
            11
        ],
        [
            [
                "Enemies"
            ],
            "Mad Sheep",
            -416.266,
            7.679,
            -43.406,
            11,
            14
        ],
        [
            [
                "Enemies"
            ],
            "Mad Sheep",
            -287.883,
            6.687,
            -44.247,
            11,
            14
        ],
        [
            [
                "Enemies"
            ],
            "Mad Sheep",
            -347.809,
            7.395,
            -39.588,
            11,
            14
        ],
        [
            [
                "Enemies"
            ],
            "Mad Sheep",
            -371.691,
            7.96,
            -41.922,
            11,
            14
        ],
        [
            [
                "Enemies"
            ],
            "Mad Sheep",
            -326.295,
            2.626,
            -51.917,
            11,
            14
        ],
        [
            [
                "Enemies"
            ],
            "Strolling Sapling",
            -322.256,
            9.907,
            -23.008,
            7,
            11
        ],
        [
            [
                "Enemies"
            ],
            "Strolling Sapling",
            -311.16,
            8.416,
            -29.65,
            7,
            11
        ],
        [
            [
                "Enemies"
            ],
            "Huge Wasp",
            -338.548,
            16.385,
            32.223,
            7,
            11
        ],
        [
            [
                "Enemies"
            ],
            "Huge Wasp",
            -284.019,
            16.797,
            63.026,
            7,
            11
        ],
        [
            [
                "Enemies"
            ],
            "Mad Sheep",
            -340.713,
            14.194,
            -7.811,
            11,
            14
        ],
        [
            [
                "Enemies"
            ],
            "Mad Sheep",
            -304.142,
            15.649,
            12.997,
            11,
            14
        ],
        [
            [
                "Enemies"
            ],
            "Mad Sheep",
            -409.109,
            8.325,
            -0.051,
            11,
            14
        ],
        [
            [
                "Enemies"
            ],
            "Mad Sheep",
            -300.065,
            15.686,
            -4.972,
            11,
            14
        ],
        [
            [
                "Enemies"
            ],
            "Mad Sheep",
            -310.238,
            14.263,
            -12.27,
            11,
            14
        ],
        [
            [
                "Enemies"
            ],
            "Strolling Sapling",
            -408.437,
            9.932,
            19.378,
            7,
            11
        ],
        [
            [
                "Enemies"
            ],
            "Strolling Sapling",
            -317.482,
            16.244,
            71.595,
            7,
            11
        ],
        [
            [
                "Enemies"
            ],
            "Wolf Zombie",
            -346.462,
            16.385,
            39.794,
            8,
            10
        ],
        [
            [
                "Enemies"
            ],
            "Goblin Thug",
            -351.14,
            17.653,
            20.863,
            8,
            10
        ],
        [
            [
                "Enemies"
            ],
            "Goblin Thug",
            -445.62,
            5.596,
            -47.321,
            8,
            10
        ],
        [
            [
                "Enemies"
            ],
            "Goblin Ambusher",
            -491.389,
            5.425,
            -41.113,
            12,
            16
        ],
        [
            [
                "Enemies"
            ],
            "Goblin Ambusher",
            -317.114,
            -12.594,
            -96.27,
            12,
            16
        ],
        [
            [
                "Enemies"
            ],
            "Goblin Weaver",
            -362.332,
            -6.352,
            -105.161,
            8,
            10
        ],
        [
            [
                "Enemies"
            ],
            "Goblin Weaver",
            -530.297,
            -3.517,
            -121.232,
            8,
            10
        ],
        [
            [
                "Enemies"
            ],
            "Goblin Weaver",
            -504.892,
            -2.654,
            -92.849,
            8,
            10
        ],
        [
            [
                "Enemies"
            ],
            "Goblin Tinkerer",
            -267.36,
            -7.594,
            -86.026,
            12,
            16
        ],
        [
            [
                "Enemies"
            ],
            "Goblin Tinkerer",
            -398.894,
            -7.35,
            -121.618,
            12,
            16
        ],
        [
            [
                "Enemies"
            ],
            "Goblin Butcher",
            -443.405,
            7.74,
            -34.818,
            12,
            16
        ],
        [
            [
                "Enemies"
            ],
            "Goblin Butcher",
            -293.112,
            16.183,
            46.898,
            12,
            16
        ],
        [
            [
                "Enemies"
            ],
            "Skeleton Warrior",
            -365.392,
            10.289,
            -25.143,
            10,
            12
        ],
        [
            [
                "Enemies"
            ],
            "Skeleton Sorcerer",
            -409.075,
            -7.404,
            -123,
            11,
            13
        ],
        [
            [
                "Enemies"
            ],
            "Grenade",
            -408.726,
            -7.683,
            -111.981,
            15,
            17
        ],
        [
            [
                "Enemies"
            ],
            "Goblin Weaver",
            -416.207,
            -2.123,
            -138.556,
            8,
            10
        ],
        [
            [
                "Enemies"
            ],
            "Goblin Tinkerer",
            -401.835,
            -0.77,
            -162.697,
            12,
            16
        ],
        [
            [
                "Enemies"
            ],
            "Goblin Butcher",
            -419.927,
            -1.628,
            -137.729,
            12,
            16
        ],
        [
            [
                "Enemies"
            ],
            "Goblin Thug",
            -516.77,
            0.199,
            48.224,
            8,
            10
        ],
        [
            [
                "Enemies"
            ],
            "Goblin Ambusher",
            -457.036,
            14.437,
            22.029,
            12,
            16
        ],
        [
            [
                "Enemies"
            ],
            "Goblin Weaver",
            -457,
            14,
            15,
            8,
            10
        ],
        [
            [
                "Enemies"
            ],
            "Huge Wasp",
            -265.894,
            16.179,
            83.95,
            7,
            11
        ],
        [
            [
                "Enemies"
            ],
            "Huge Wasp",
            -207.19,
            16.057,
            118.505,
            7,
            11
        ],
        [
            [
                "Enemies"
            ],
            "Mad Sheep",
            -242.35,
            15.382,
            130.056,
            11,
            14
        ],
        [
            [
                "Enemies"
            ],
            "Mad Sheep",
            -165.358,
            -6.626,
            11.518,
            11,
            14
        ],
        [
            [
                "Enemies"
            ],
            "Mad Sheep",
            -192.169,
            16.161,
            150.273,
            11,
            14
        ],
        [
            [
                "Enemies"
            ],
            "Mad Sheep",
            -170.91,
            -2.111,
            17.204,
            11,
            14
        ],
        [
            [
                "Enemies"
            ],
            "Strolling Sapling",
            -193.743,
            15.727,
            104.013,
            7,
            11
        ],
        [
            [
                "Enemies"
            ],
            "Strolling Sapling",
            -267.71,
            16.146,
            122.522,
            7,
            11
        ],
        [
            [
                "Enemies"
            ],
            "Wolf Zombie",
            -235.061,
            16.179,
            62.048,
            8,
            10
        ],
        [
            [
                "Enemies"
            ],
            "Mist Lizard",
            37.776,
            25.694,
            100.565,
            10,
            12
        ],
        [
            [
                "Enemies"
            ],
            "Mist Lizard",
            -124.106,
            3.105,
            96.303,
            10,
            12
        ],
        [
            [
                "Enemies"
            ],
            "Mist Lizard",
            -121.159,
            15.959,
            192.146,
            10,
            12
        ],
        [
            [
                "Enemies"
            ],
            "Huge Wasp",
            -20.377,
            10.973,
            57.164,
            7,
            11
        ],
        [
            [
                "Enemies"
            ],
            "Huge Wasp",
            -110.187,
            15.679,
            201.149,
            7,
            11
        ],
        [
            [
                "Enemies"
            ],
            "Huge Wasp",
            23.786,
            24.612,
            98.126,
            7,
            11
        ],
        [
            [
                "Enemies"
            ],
            "Mad Sheep",
            -117.47,
            17.649,
            179.461,
            11,
            14
        ],
        [
            [
                "Enemies"
            ],
            "Mad Sheep",
            -23.76,
            24.094,
            143.5,
            11,
            14
        ],
        [
            [
                "Enemies"
            ],
            "Strolling Sapling",
            -5.794,
            23.965,
            116.45,
            7,
            11
        ],
        [
            [
                "Enemies"
            ],
            "Strolling Sapling",
            -94.607,
            16.258,
            132.585,
            7,
            11
        ],
        [
            [
                "Enemies"
            ],
            "Strolling Sapling",
            -108.899,
            9.108,
            102.933,
            7,
            11
        ],
        [
            [
                "Enemies"
            ],
            "Mist Lizard",
            31.283,
            23.646,
            119.293,
            10,
            12
        ],
        [
            [
                "Enemies"
            ],
            "Mist Lizard",
            81.433,
            24.005,
            131.512,
            10,
            12
        ],
        [
            [
                "Enemies"
            ],
            "Mist Lizard",
            112.69,
            16.277,
            86.202,
            10,
            12
        ],
        [
            [
                "Enemies"
            ],
            "Huge Wasp",
            97.412,
            25.639,
            307.538,
            7,
            11
        ],
        [
            [
                "Enemies"
            ],
            "Huge Wasp",
            133.932,
            23.691,
            272.197,
            7,
            11
        ],
        [
            [
                "Enemies"
            ],
            "Huge Wasp",
            21.576,
            31.637,
            266.038,
            7,
            11
        ],
        [
            [
                "Enemies"
            ],
            "Huge Wasp",
            92.501,
            23.942,
            283.316,
            7,
            11
        ],
        [
            [
                "Enemies"
            ],
            "Strolling Sapling",
            85.546,
            25.572,
            299.375,
            7,
            11
        ],
        [
            [
                "Enemies"
            ],
            "Strolling Sapling",
            57.736,
            23.556,
            167.877,
            7,
            11
        ],
        [
            [
                "Enemies"
            ],
            "Strolling Sapling",
            171.849,
            23.426,
            123.046,
            7,
            11
        ],
        [
            [
                "Enemies"
            ],
            "Strolling Sapling",
            130.324,
            29.236,
            368.29,
            7,
            11
        ],
        [
            [
                "Enemies"
            ],
            "Strolling Sapling",
            129.762,
            23.541,
            228.52,
            7,
            11
        ],
        [
            [
                "Enemies"
            ],
            "Strolling Sapling",
            99.896,
            24.237,
            158.377,
            7,
            11
        ],
        [
            [
                "Enemies"
            ],
            "Mist Lizard",
            43.954,
            32.015,
            355.865,
            10,
            12
        ],
        [
            [
                "Enemies"
            ],
            "Mist Lizard",
            -32.385,
            16.524,
            256.354,
            10,
            12
        ],
        [
            [
                "Enemies"
            ],
            "Mist Lizard",
            31.619,
            32.916,
            355.227,
            10,
            12
        ],
        [
            [
                "Enemies"
            ],
            "Huge Wasp",
            92.228,
            30.532,
            355.147,
            7,
            11
        ],
        [
            [
                "Enemies"
            ],
            "Huge Wasp",
            11.582,
            32.672,
            383.923,
            7,
            11
        ],
        [
            [
                "Enemies"
            ],
            "Huge Wasp",
            95.229,
            31.629,
            393.755,
            7,
            11
        ],
        [
            [
                "Enemies"
            ],
            "Huge Wasp",
            -6.121,
            28.372,
            313.331,
            7,
            11
        ],
        [
            [
                "Enemies"
            ],
            "Strolling Sapling",
            71.913,
            26.336,
            335.107,
            7,
            11
        ],
        [
            [
                "Enemies"
            ],
            "Strolling Sapling",
            -35.268,
            24.98,
            336.103,
            7,
            11
        ],
        [
            [
                "Enemies"
            ],
            "Strolling Sapling",
            -17.077,
            23.121,
            211.57,
            7,
            11
        ],
        [
            [
                "Enemies"
            ],
            "Strolling Sapling",
            -9.89,
            31.602,
            350.609,
            7,
            11
        ],
        [
            [
                "Enemies"
            ],
            "Strolling Sapling",
            57.296,
            27.094,
            316.368,
            7,
            11
        ],
        [
            [
                "Enemies"
            ],
            "Strolling Sapling",
            -30.941,
            16.898,
            244.216,
            7,
            11
        ],
        [
            [
                "Enemies"
            ],
            "Tremor Ram",
            21,
            50,
            514,
            21,
            23
        ],
        [
            [
                "Enemies"
            ],
            "Rampaging Ram",
            160,
            24,
            121,
            27,
            28
        ],
        [
            [
                "Enemies"
            ],
            "Steelfleece Baldarich",
            -10,
            7,
            45,
            55,
            56
        ],
        [
            [
                "Enemies"
            ],
            "Young Quadav",
            -58.29,
            19.993,
            170.944,
            8,
            10
        ],
        [
            [
                "Enemies"
            ],
            "Veteran Quadav",
            31.138,
            31.181,
            279.142,
            10,
            16
        ],
        [
            [
                "Enemies"
            ],
            "Greater Quadav",
            -48.357,
            22.944,
            157.082,
            10,
            16
        ],
        [
            [
                "Enemies"
            ],
            "Onyx Quadav",
            -43.285,
            23.709,
            129.506,
            10,
            16
        ],
        [
            [
                "Enemies"
            ],
            "Amethyst Quadav",
            120.91,
            25.134,
            333.69,
            8,
            10
        ],
        [
            [
                "Enemies"
            ],
            "Amber Quadav",
            16.43,
            33.668,
            317.535,
            8,
            10
        ],
        [
            [
                "Enemies"
            ],
            "Skeleton Warrior",
            -37.801,
            31.56,
            365.201,
            10,
            12
        ],
        [
            [
                "Enemies"
            ],
            "Skeleton Sorcerer",
            -43.67,
            15.382,
            228.732,
            11,
            13
        ],
        [
            [
                "Enemies"
            ],
            "Ghost",
            145.403,
            23.314,
            328.634,
            15,
            17
        ],
        [
            [
                "Enemies"
            ],
            "Grenade",
            91.756,
            31.798,
            375.136,
            15,
            17
        ],
        [
            [
                "Enemies"
            ],
            "Earth Elemental",
            153.706,
            25.947,
            380.316,
            18,
            20
        ],
        [
            [
                "Enemies"
            ],
            "Huge Wasp",
            -253.292,
            17.686,
            210.338,
            7,
            11
        ],
        [
            [
                "Enemies"
            ],
            "Huge Wasp",
            -246.899,
            17.114,
            209.235,
            7,
            11
        ],
        [
            [
                "Enemies"
            ],
            "Huge Wasp",
            -365.239,
            24.284,
            283.399,
            7,
            11
        ],
        [
            [
                "Enemies"
            ],
            "Mad Sheep",
            -348.821,
            15.891,
            189.028,
            11,
            14
        ],
        [
            [
                "Enemies"
            ],
            "Mad Sheep",
            -198.288,
            22.359,
            231.806,
            11,
            14
        ],
        [
            [
                "Enemies"
            ],
            "Mad Sheep",
            -344.333,
            15.798,
            177.111,
            11,
            14
        ],
        [
            [
                "Enemies"
            ],
            "Mad Sheep",
            -269.326,
            24.327,
            177.639,
            11,
            14
        ],
        [
            [
                "Enemies"
            ],
            "Strolling Sapling",
            -367.442,
            17.6,
            250.331,
            7,
            11
        ],
        [
            [
                "Enemies"
            ],
            "Strolling Sapling",
            -326.983,
            16.028,
            168.777,
            7,
            11
        ],
        [
            [
                "Enemies"
            ],
            "Wolf Zombie",
            -317.749,
            19.378,
            226.035,
            8,
            10
        ],
        [
            [
                "Enemies"
            ],
            "Mist Lizard",
            -485.444,
            15.016,
            258.927,
            10,
            12
        ],
        [
            [
                "Enemies"
            ],
            "Mist Lizard",
            -476.976,
            16.062,
            306.094,
            10,
            12
        ],
        [
            [
                "Enemies"
            ],
            "Mist Lizard",
            -375.551,
            27.853,
            374.034,
            10,
            12
        ],
        [
            [
                "Enemies"
            ],
            "Huge Wasp",
            -397.546,
            15.874,
            231.916,
            7,
            11
        ],
        [
            [
                "Enemies"
            ],
            "Huge Wasp",
            -402.85,
            15.72,
            225.889,
            7,
            11
        ],
        [
            [
                "Enemies"
            ],
            "Huge Wasp",
            -433.126,
            24.203,
            300.786,
            7,
            11
        ],
        [
            [
                "Enemies"
            ],
            "Mad Sheep",
            -376.042,
            27.595,
            349.055,
            11,
            14
        ],
        [
            [
                "Enemies"
            ],
            "Mad Sheep",
            -416.793,
            16.134,
            203.9,
            11,
            14
        ],
        [
            [
                "Enemies"
            ],
            "Strolling Sapling",
            -407.033,
            17.637,
            258.944,
            7,
            11
        ],
        [
            [
                "Enemies"
            ],
            "Strolling Sapling",
            -542.023,
            10.276,
            238.412,
            7,
            11
        ],
        [
            [
                "Enemies"
            ],
            "Rock Eater",
            -608.988,
            6.865,
            209.44,
            7,
            11
        ],
        [
            [
                "Enemies"
            ],
            "Rock Eater",
            -646.112,
            6.744,
            152.706,
            7,
            11
        ],
        [
            [
                "Enemies"
            ],
            "Rock Eater",
            -591.892,
            6.914,
            230.358,
            7,
            11
        ],
        [
            [
                "Enemies"
            ],
            "Rock Eater",
            -604.658,
            6.65,
            228.666,
            7,
            11
        ],
        [
            [
                "Enemies"
            ],
            "Rock Eater",
            -620.555,
            6.968,
            193.688,
            7,
            11
        ],
        [
            [
                "Enemies"
            ],
            "Ghost",
            -710.913,
            2.309,
            101.913,
            15,
            17
        ],
        [
            [
                "Enemies"
            ],
            "Earth Elemental",
            -700.529,
            2.963,
            104.203,
            18,
            20
        ],
        [
            [
                "Enemies"
            ],
            "Huge Wasp",
            -282.166,
            32.214,
            347.932,
            7,
            11
        ],
        [
            [
                "Enemies"
            ],
            "Huge Wasp",
            -200.524,
            39.031,
            313.235,
            7,
            11
        ],
        [
            [
                "Enemies"
            ],
            "Mad Sheep",
            -293.9,
            33.393,
            342.71,
            11,
            14
        ],
        [
            [
                "Enemies"
            ],
            "Mad Sheep",
            -287.231,
            33.606,
            370.184,
            11,
            14
        ],
        [
            [
                "Enemies"
            ],
            "Mad Sheep",
            -267.999,
            38.243,
            375.792,
            11,
            14
        ],
        [
            [
                "Enemies"
            ],
            "Mad Sheep",
            -241.079,
            41.5,
            370.69,
            11,
            14
        ],
        [
            [
                "Enemies"
            ],
            "Mad Sheep",
            -196.172,
            39.019,
            364.924,
            11,
            14
        ],
        [
            [
                "Enemies"
            ],
            "Stray Mary",
            -212.268,
            39.477,
            329.581,
            19,
            20
        ],
        [
            [
                "Enemies"
            ],
            "Strolling Sapling",
            -236.657,
            48.537,
            407.58,
            7,
            11
        ],
        [
            [
                "Enemies"
            ],
            "Strolling Sapling",
            -202.888,
            42.076,
            377.649,
            7,
            11
        ],
        [
            [
                "Enemies"
            ],
            "Wolf Zombie",
            -303.063,
            35.144,
            358.863,
            8,
            10
        ],
        [
            [
                "Enemies"
            ],
            "Huge Wasp",
            -172.615,
            32.425,
            352.625,
            7,
            11
        ],
        [
            [
                "Enemies"
            ],
            "Huge Wasp",
            -174.03,
            33.518,
            328.957,
            7,
            11
        ],
        [
            [
                "Enemies"
            ],
            "Mad Sheep",
            -199.627,
            31.887,
            279.948,
            11,
            14
        ],
        [
            [
                "Enemies"
            ],
            "Mad Sheep",
            -149.799,
            34.637,
            373.558,
            11,
            14
        ],
        [
            [
                "Enemies"
            ],
            "Mad Sheep",
            -180.461,
            29.707,
            286.903,
            11,
            14
        ],
        [
            [
                "Enemies"
            ],
            "Mad Sheep",
            -69.298,
            29.682,
            354.51,
            11,
            14
        ],
        [
            [
                "Enemies"
            ],
            "Strolling Sapling",
            -68.612,
            32.495,
            363.465,
            7,
            11
        ],
        [
            [
                "Enemies"
            ],
            "Strolling Sapling",
            -120.629,
            32.208,
            360.805,
            7,
            11
        ],
        [
            [
                "Enemies"
            ],
            "Wolf Zombie",
            -115.37,
            22.901,
            326.005,
            8,
            10
        ],
        [
            [
                "Enemies"
            ],
            "Goblin Tinkerer",
            -111.048,
            11.646,
            270.473,
            12,
            16
        ],
        [
            [
                "Enemies"
            ],
            "Goblin Thug",
            -272.05,
            47.916,
            438.28,
            8,
            10
        ],
        [
            [
                "Enemies"
            ],
            "Goblin Ambusher",
            -437.997,
            23.814,
            289.64,
            12,
            16
        ],
        [
            [
                "Enemies"
            ],
            "Goblin Ambusher",
            -271.111,
            23.983,
            176.806,
            12,
            16
        ],
        [
            [
                "Enemies"
            ],
            "Goblin Weaver",
            -419.973,
            18.267,
            251.836,
            8,
            10
        ],
        [
            [
                "Enemies"
            ],
            "Goblin Weaver",
            -323.749,
            33.429,
            299.87,
            8,
            10
        ],
        [
            [
                "Enemies"
            ],
            "Goblin Tinkerer",
            -332.61,
            31.912,
            301.545,
            12,
            16
        ],
        [
            [
                "Enemies"
            ],
            "Goblin Butcher",
            -101.245,
            25.323,
            345.416,
            12,
            16
        ],
        [
            [
                "Enemies"
            ],
            "Goblin Butcher",
            -302.195,
            34.384,
            359.779,
            12,
            16
        ],
        [
            [
                "Enemies"
            ],
            "Skeleton Warrior",
            -314.998,
            30.755,
            271.463,
            10,
            12
        ],
        [
            [
                "Enemies"
            ],
            "Skeleton Sorcerer",
            -191.612,
            38.647,
            318.807,
            11,
            13
        ],
        [
            [
                "Enemies"
            ],
            "Thunder Elemental",
            -262.45,
            37.507,
            298.166,
            18,
            20
        ],
        [
            [
                "Enemies"
            ],
            "Mist Lizard",
            -226.308,
            55.074,
            499.403,
            10,
            12
        ],
        [
            [
                "Enemies"
            ],
            "Mist Lizard",
            -114.16,
            53.858,
            511.536,
            10,
            12
        ],
        [
            [
                "Enemies"
            ],
            "Huge Wasp",
            -200.992,
            55.263,
            472.933,
            7,
            11
        ],
        [
            [
                "Enemies"
            ],
            "Huge Wasp",
            -110.59,
            49.154,
            461.188,
            7,
            11
        ],
        [
            [
                "Enemies"
            ],
            "Mad Sheep",
            -79.219,
            40.243,
            419.502,
            11,
            14
        ],
        [
            [
                "Enemies"
            ],
            "Mad Sheep",
            -182.413,
            61.025,
            507.831,
            11,
            14
        ],
        [
            [
                "Enemies"
            ],
            "Mad Sheep",
            -124.758,
            46.843,
            395.038,
            11,
            14
        ],
        [
            [
                "Enemies"
            ],
            "Strolling Sapling",
            -151.138,
            48.443,
            444.856,
            7,
            11
        ],
        [
            [
                "Enemies"
            ],
            "Strolling Sapling",
            -76.391,
            47.095,
            437.487,
            7,
            11
        ],
        [
            [
                "Enemies"
            ],
            "Wolf Zombie",
            -129.429,
            48.88,
            448.089,
            8,
            10
        ],
        [
            [
                "Enemies"
            ],
            "Mist Lizard",
            -53.891,
            61.019,
            551.878,
            10,
            12
        ],
        [
            [
                "Enemies"
            ],
            "Mist Lizard",
            39.121,
            55.307,
            562.402,
            10,
            12
        ],
        [
            [
                "Enemies"
            ],
            "Mist Lizard",
            -10.088,
            41.101,
            462.604,
            10,
            12
        ],
        [
            [
                "Enemies"
            ],
            "Huge Wasp",
            -3.054,
            47.224,
            492.709,
            7,
            11
        ],
        [
            [
                "Enemies"
            ],
            "Huge Wasp",
            5.772,
            50.656,
            508.624,
            7,
            11
        ],
        [
            [
                "Enemies"
            ],
            "Mad Sheep",
            -70.546,
            60.651,
            590.867,
            11,
            14
        ],
        [
            [
                "Enemies"
            ],
            "Mad Sheep",
            -36.803,
            38.999,
            436.784,
            11,
            14
        ],
        [
            [
                "Enemies"
            ],
            "Mad Sheep",
            -26.991,
            40.043,
            445.767,
            11,
            14
        ],
        [
            [
                "Enemies"
            ],
            "Strolling Sapling",
            29.173,
            54.945,
            553.949,
            7,
            11
        ],
        [
            [
                "Enemies"
            ],
            "Strolling Sapling",
            -38.41,
            65.063,
            588.457,
            7,
            11
        ],
        [
            [
                "Enemies"
            ],
            "Mist Lizard",
            -182.885,
            63.846,
            546.826,
            10,
            12
        ],
        [
            [
                "Enemies"
            ],
            "Mist Lizard",
            -242.412,
            69.623,
            804.25,
            10,
            12
        ],
        [
            [
                "Enemies"
            ],
            "Mist Lizard",
            -144.661,
            59.622,
            556.399,
            10,
            12
        ],
        [
            [
                "Enemies"
            ],
            "Huge Wasp",
            -154.289,
            72.074,
            704.687,
            7,
            11
        ],
        [
            [
                "Enemies"
            ],
            "Huge Wasp",
            -180.776,
            67.439,
            610.628,
            7,
            11
        ],
        [
            [
                "Enemies"
            ],
            "Mad Sheep",
            -237.864,
            69.753,
            762.71,
            11,
            14
        ],
        [
            [
                "Enemies"
            ],
            "Mad Sheep",
            -222.549,
            70.86,
            636.883,
            11,
            14
        ],
        [
            [
                "Enemies"
            ],
            "Strolling Sapling",
            -298.84,
            58.113,
            609.951,
            7,
            11
        ],
        [
            [
                "Enemies"
            ],
            "Strolling Sapling",
            -285.782,
            55.255,
            569.554,
            7,
            11
        ],
        [
            [
                "Enemies"
            ],
            "Tremor Ram",
            -163.198,
            62.392,
            568.282,
            21,
            23
        ],
        [
            [
                "Enemies"
            ],
            "Goblin Ambusher",
            8.997,
            37.803,
            441.582,
            12,
            16
        ],
        [
            [
                "Enemies"
            ],
            "Goblin Tinkerer",
            -148.111,
            71.708,
            654.867,
            12,
            16
        ],
        [
            [
                "Enemies"
            ],
            "Goblin Butcher",
            -39.868,
            68.265,
            566.478,
            12,
            16
        ],
        [
            [
                "Enemies"
            ],
            "Veteran Quadav",
            -167.325,
            63.785,
            589.155,
            10,
            16
        ],
        [
            [
                "Enemies"
            ],
            "Greater Quadav",
            -129.975,
            47.678,
            399.49,
            10,
            16
        ],
        [
            [
                "Enemies"
            ],
            "Onyx Quadav",
            -103.799,
            50.135,
            458.197,
            10,
            16
        ],
        [
            [
                "Enemies"
            ],
            "Skeleton Warrior",
            -155.997,
            59.753,
            511.91,
            10,
            12
        ],
        [
            [
                "Enemies"
            ],
            "Skeleton Sorcerer",
            -176.029,
            53.167,
            463.645,
            11,
            13
        ],
        [
            [
                "Enemies"
            ],
            "Thunder Elemental",
            -154.221,
            49.092,
            420.093,
            18,
            20
        ],
        [
            [
                "Enemies"
            ],
            "Goblin Digger",
            -82.375,
            70.154,
            676.15,
            11,
            14
        ],
        [
            [
                "Enemies"
            ],
            "Goblin Archaeologist",
            141.024,
            23.679,
            248.83,
            30,
            75
        ],
        [
            [
                "Enemies"
            ],
            "Forger",
            -710,
            2,
            102,
            33,
            33
        ],
        [
            [
                "Enemies"
            ],
            "Haty",
            -204.271,
            8.118,
            36.959,
            14,
            14
        ],
        [
            [
                "Enemies"
            ],
            "Bendigeit Vran",
            -2.11,
            24.44,
            105.396,
            14,
            14
        ],
        [
            [
                "Enemies"
            ],
            "Gwynn ap Nudd",
            -125.0,
            71.549,
            720.0,
            94,
            95
        ],
        [
            [
                "Enemies"
            ],
            "Gwynn ap Nudd",
            397.728,
            -1.861,
            -4.327,
            94,
            95
        ],
        [
            [
                "Enemies"
            ],
            "Gwynn ap Nudd",
            200.0,
            -24.5,
            -400.0,
            94,
            95
        ],
        [
            [
                "Enemies"
            ],
            "Otherworldly Rimester",
            208.462,
            23.534,
            309.907,
            0,
            0
        ]
    ],
    "entities": [
        [
            [
                "???"
            ],
            "???",
            -201.531,
            16.0,
            82.714
        ],
        [
            [
                "???"
            ],
            "???",
            -709.195,
            2.681,
            102.29
        ],
        [
            [
                "Home Point"
            ],
            "Telepoint",
            220.0,
            19.104,
            300.0
        ],
        [
            [
                "Home Point"
            ],
            "Dimensional Portal",
            220.0,
            19.104,
            140.0
        ],
        [
            [
                "Home Point"
            ],
            "Shattered Telepoint",
            140.0,
            19.104,
            220.0
        ],
        [
            [
                "NPC"
            ],
            "Stone Monument",
            -102.355,
            7.981,
            253.706
        ],
        [
            [
                "NPC"
            ],
            "Plaiaude",
            244.705,
            24.034,
            296.973
        ],
        [
            [
                "NPC"
            ],
            "Ramblix",
            90.618,
            -70.15,
            -589.455
        ],
        [
            [
                "Field Manual"
            ],
            "Field Manual",
            -285.839,
            -48.539,
            -421.089
        ],
        [
            [
                "Field Manual"
            ],
            "Field Manual",
            203.023,
            23.999,
            283.554
        ],
        [
            [
                "NPC"
            ],
            "Clemaurent",
            172.25,
            24.0,
            291.181
        ]
    ]
}